airbeld/__init__.py
airbeld/auth.py
airbeld/client.py
airbeld/exceptions.py
airbeld/models.py
airbeld/py.typed
airbeld/version.py
airbeld_api_sdk-0.4.0.dist-info/METADATA
airbeld_api_sdk-0.4.0.dist-info/WHEEL
airbeld_api_sdk-0.4.0.dist-info/licenses/LICENSE
airbeld_api_sdk-0.4.0.dist-info/RECORD
