Metadata-Version: 2.4
Name: airbeld-api-sdk
Version: 0.4.0
Summary: Async Python SDK for the Airbeld backend
Project-URL: Changelog, https://github.com/Embio-Diagnostics/airbeld-api-sdk/blob/main/CHANGELOG.md
Project-URL: Documentation, https://github.com/Embio-Diagnostics/airbeld-api-sdk/blob/main/README.md
Project-URL: Homepage, https://github.com/Embio-Diagnostics/airbeld-api-sdk
Project-URL: Issues, https://github.com/Embio-Diagnostics/airbeld-api-sdk/issues
Project-URL: Repository, https://github.com/Embio-Diagnostics/airbeld-api-sdk
Author-email: Embio Diagnostics Ltd <l.dougiakis@embiodiagnostics.eu>
License: MIT
License-File: LICENSE
Keywords: air-quality,airbeld,home-assistant
Classifier: License :: OSI Approved :: MIT License
Classifier: Programming Language :: Python :: 3
Classifier: Programming Language :: Python :: 3 :: Only
Classifier: Typing :: Typed
Requires-Python: >=3.10
Requires-Dist: httpx>=0.28.1
Requires-Dist: pydantic>=2.11.7
Requires-Dist: tenacity>=9.1.2
Provides-Extra: dev
Requires-Dist: httpx>=0.27; extra == 'dev'
Requires-Dist: mypy>=1.10; extra == 'dev'
Requires-Dist: pydantic>=2.7; extra == 'dev'
Requires-Dist: pytest-asyncio>=0.23; extra == 'dev'
Requires-Dist: pytest>=8; extra == 'dev'
Requires-Dist: ruff>=0.5; extra == 'dev'
Requires-Dist: tenacity>=8.2; extra == 'dev'
